rdp.cpython-37m-x86_64-linux-gnu.so
rdp.pyx
rdp_package-0.1.1.dist-info/METADATA
rdp_package-0.1.1.dist-info/WHEEL
rdp_package-0.1.1.dist-info/RECORD
