Metadata-Version: 2.1
Name: rdp-package
Version: 0.1.1
Summary: 
Requires-Python: >=3.7,<4.0
Classifier: Programming Language :: Python :: 3
Classifier: Programming Language :: Python :: 3.7
Classifier: Programming Language :: Python :: 3.8
Classifier: Programming Language :: Python :: 3.9
Classifier: Programming Language :: Python :: 3.10
Classifier: Programming Language :: Python :: 3.11
Requires-Dist: cython (==3.0.12)
Requires-Dist: numpy (==1.21.1)
Requires-Dist: wheel (==0.41.0)
